{"@context": "https://www.europeana.eu/schemas/context/edm.jsonld", "id": "https://www.europeana.eu/api/fulltext/9200300/BibliographicResource_3000051823564/d431a4271ad0a80bab3ad79318179231", "type": "FullTextResource", "edmRights": "http://creativecommons.org/publicdomain/mark/1.0/", "language": "de", "value": "SSO\nVertheidigung u\u00abd Nothwehr anzusehen ; denn diese Schiffe haben sich der K\u00fcste zur Nachtzeit unter Umst\u00e4nden, welche gerechte Besorgnisse eineS LandungSversucheS einfl\u00f6\u00dfen mu\u00dften, genarrt, nachdem der k. Admiral wenige Tage vorher dem Befehlshaber des Oesterreichischen Geschwa ders erkl\u00e4rt hatte, denselben , wo immer er ihn antreffiln w\u00fcrde, angreifen zu \"wollen und diese Drohurg in seiner Corresvonden; mit den fremden Consuln nicht nur erneuert, sondern selbst mit einem in Aussicht gestellten Angriffe a^f Triest versch\u00e4rft hatte. Es mag der Sardimscheu F lotte vielleicht zustehen, eine Stellung in den Venetianischen Gew\u00e4ssern einzunehmen und diese K\u00fcsten gegen Angriffe zur See zu sch\u00fctzen; eine \u00fcber diesen Bereich, wie \u00fcber diesen Zveck hinaus gehende Wirksamkeit derselben , in sofern sie Gebiethe und Rechte des Deutschen Reiches iq, Entferntesten ber\u00fchrt, k\u00f6nnen und d\u00fcrfen nimmer gedul det werden. Zu diesen Rechten geh\u00f6rt unstreitig jenes eines unge hinderten Verkehrs des Deutschen Freihafens von Triest. Die von dort auskaufenden und in denselben einlaufenden Schiffe d\u00fcrfen unter keinem Vornmnde angehalten, und \u00bboch weniger einer Untersuchung unterzogen werden, denn die Freiheit der offenen See, wie jene eines Deutschen Hafens jubeeintr\u00e4chtigen, steht keiner mit dem Deutschen Reiche in Frieden lebenden Macht zu. Der Vorwand des Rechtes, den Transport von KriegSbedarf zu verhin dern , mu\u00df gleichfalls mit Entschiedenheit zur\u00fcckgewiesen werden; den abgesehen von dem Umst\u00e4nde, da\u00df jedeS Kauffahrteischiff befugt ist, und auch sein mu\u00df, zu Sig nal - und Nothsch\u00fcssen, wie zur Vertheidigung gegen Seer\u00e4uber, daS n\u00f6thige Material mit sich zu f\u00fchren, mu\u00df auch jedeS neutrale Gebieth, wie daS Deutsche ei offenbar ist, berechtiget sein, ungehindert selbst Waffen ein- und auszuf\u00fchren. Sollte eine solche Ausfuhr mit der Bestimmung geschehen, die K\u00fcsten zu bedrohen, zu deren Schutze Sardinien sich berufen glaubt, so mag die Flotte daselbst eine Landung verh\u00fcthen. Weiter zu gehen kann ihr nicht gestattet werden. Endlich ist eS eine bisher nicht gekannte Anforderung, die Landung an jedem beliebigen Puncte der K\u00fcste sich vorbehalten, und gegen jede\u00bb Widerstand dabei protesti-ren wollen, w\u00e4hrend doch durch die angeordneten Blocka de-Ma\u00dfregeln eine offenbar feindliche Stellung einge nommen worden ist, welche die gegr\u00fcndete Besorgni\u00df ein fl\u00f6\u00dfen mu\u00df, da\u00df mit einer Landung auch ein Angriff ge gen die Stadt und bey Hafen von Triest beabsichtigt wer den k\u00f6nnte. Der Unterzeichnete findet daher, da\u00df der angebliche Neutralit\u00e4tS-Zustand zur See keineswegs eingetreten sei, vielmehr thats\u00e4chlich die Blockade von Trieft \u2014 eineS zum Deutschen BundeSgebiethe geh\u00f6rigen Hafens fortw\u00e4hre, und der Stand der Di^ige im Wesentlichen noch immer jeoer sei, der die Einlegung einer feierlichen Protesta tion von Seiten der Bundesversammlung unterm 46 Juni 1848 veranla\u00dft hat, und wor\u00fcber E. E. die Erwiede rung gegeben haben, da\u00df die k\u00f6niglich Sardinische Re gierung , die mit dem Deutschen Bund\u00ab in freundlicher Beziehung zu bleiben w\u00fcnscht, darauf bedacht sein m\u00fcsse, daS Gebieth der L\u00e4nder, welche Bestandtheile deS Bun des bilden, nicht zu verletzen, und daher die Aufhebung der Blockade von Triest beschlossen habe. Der unterzeichnete Reichs-Minister der ausw\u00e4rtigen Angelegenheiten kann in daS Verh\u00e4lmi\u00df, welches zwischen der k\u00f6niglich Sardinischen Regierung und Oesten eich zur See besteht, nicht n\u00e4her eingehen \u2014 von Feindseligkeiten Seitens der Oesterreichischen Flott\u00ab wurde \u00fcbrigens nichts bekannr; \u2014 er ber\u00fccksichtiget nur, da\u00df durch die von dem Herrn Admiral Albini erlassenen Anordnungen die Deut schen Handelsschiffe den auffallendsten Behelligungen aus gesetzt sind, und die freie Schifffahrt offenbar gehemmt wird, da\u00df durch die in Anspruch genommene Landung an belie bigen K\u00fcstenpuncten Triest mit seinem Gebiethe forrw\u00e4h-revden Angriffen ausgesetzt ist, sich daher im Zustande der Vertheidigung halten mu\u00df, und da\u00df eS nur von irgend emttt, Zufalle abh\u00e4ngt, ob nicht ein Zusemmensto\u00df der milit\u00e4rischen Kr\u00e4fte Statt finde.\nOffenbar dauern daher jene\"Vech\u00e4lmisse fort, welch\u00abz\u00bb einem Uebergange am untern Po, sich \u00fcber den C\u00bb\nnach Art. Nr. 39 der Wiener Schl\u00fcssele den Stand deS Krieges vermuthen und besorgen lassen und welche eS da her zur gebietherischen Pflicht machen, ihre unges\u00e4umte Aenderung zu bewirken. ^ Der Unterzeichnete kann E. E. nicht verbergen, da\u00df solche Vo g\u00e4nge, wie sie gegen das Gebieth von Triest und den^ T eutschen Handel stattfinden, wenig geeignet sind, ^eb^afle Sympathie f\u00fcr die Sardinische Regierung zu er-wecken, und da\u00df sich nicht nur die \u00f6ffentliche Meinung in \" entschland in diesem Sinne ansspricht, sondern insbs-ndere die in Frankfurt versammele Deutsche National ersammlung in ihren Verhandlungen und nahmentlich in j^ener am 20. Juni Nr. 48 unumwunden dahin sich erkl\u00e4rt hat, da\u00df ein Angriff gegen Triest und sein Gebieth alS eine Kriegserkl\u00e4rung gegen den Deutschen Bund betrachtet werde. E. E. wird eS kaum entgangen sein, welche Ueberein stimmung gegenw\u00e4rtig in ganz Deutschland darin herrsche, da\u00df seine Ehre und Unabh\u00e4ngigkeit bewahrt werden m\u00fcsse und da\u00df zum kr\u00e4ftigen Schutze Deutscher Interessen die provisorische Cevtral-Geivalt geschaffen worden iit? E. E. werden daher ermessen, da\u00df eS der k\u00f6niglich Sardinischen Regierung unter den gegenw\u00e4rtigen Verh\u00e4ltnissen empfeh-lenSwerrh sein d\u00fcrfte, AlleS zu vermeiden, waS gegr\u00fcndete Beschwerden von Seiren Deutschlands herbeif\u00fchren und asif dessen Ber\u00fccksichtigung gedrungen werden mu\u00df. Dahin geh\u00f6rt die thats\u00e4chlich bestehende Blockade deS HafenS von Triest, auf deren f\u00f6rmliche Aufhebung daher die Tentral-Gewalt f\u00fcr Deutschland um so mehr die be stimmte Anforderung stellen mu\u00df, alS die k\u00f6niglich Sar dinische Regierung sie bereit\u00bb zugesichert hat und die Ver z\u00f6gerung in der Ausf\u00fchrung dieser Zusicherung durchaus nicht gerechtfertigt erscheint. Der unterzeichnete Reichs-Minister der auSw\u00e4rtigesAnge-legenheiten zweifelt nicht, da\u00df die k\u00f6nigl. Sardinische Regie rung unter den dargestslltenVerh\u00e4ltnissen sofort an den Hrn. Admiral Albini den Befehl erlassen wird, die Blockade det HafenS von Triest f\u00f6rmlich und vollst\u00e4ndig aufzuheben uqd jede Behelligung deS Handels zu unterlassen. Indem ich mir daher erlaube , E. E. zu ersuchen, von disser Zuschrift ihrer Regierung die Mittheilung zu ma chen, ben\u00fctze ich diesen Anla\u00df, E. E. meine ausgezeich netste Hochachtung zu versichern-Frankfurt am 22. Juli 4848. Der ReichS-Minister der ausw\u00e4ct. Angelegenheiten. Gez. Schmerling.\nLombardifch Benetianisches K\u00f6nigreich. Schlu\u00df der estern abgebrochenen Zusammenstellung der Ereignisse bei dem nunmehrigen 2ten Reserve-TorpS deS Felldmarschall-LieutenautSWelden vom 9- bis 24.Juli 1848-Am 47. gegen Einbruch der Nacht r\u00fcckce denn auch daS 4.! Bataillon Koudelka Infanterie von Padua \u00fcber Ro-vigo nach Santa M. Maddalena ab, besetzte Pvnte di laAv scuro und Stellata auf dem rechten Po-Ufer, welche Orte sogleich zur Vertheidigung Hergerichret wurden, und lie\u00df Abtheilungen nach Bondens streifen, woselbst man nichts vom Feinde gewahrte. Der Herr F. M. L. PerglaS, welchem daS CoM-mapbo \u00fcber diese Truppen-Abtheilungen, au\u00dfer den vor genannten BataillovS Koudelka-Jnfanterie, auS 4 Es-cadjron Boyneburg Dragoner, und einer Halden Cavalle-rie-iBatterie bestehend, der Tags darauf 2 Compagnien Kojidelka-Jnfanterie und eine halbpf\u00fcndige Batterie mir der! Bestimmung nach Boara folgten, \u00fcbertragen worden was, sollte nicht nur die kr\u00e4ftigsten Ma\u00dfregeln zur Ver wesung jedes Po-Uebergange\u00ab ergreifen, we\u00dfhalb dieser Getieral, dem vorgenannten wichtigen Puncte am rechten PosUfer, vorz\u00fcglich aber dem rechten Fl\u00fcgel seiner Auf stellung ein strenges Augenmerk zuwendend, Streifangen gegtn Massa und Ostiglia am linken Ufer aufw\u00e4rts, vor zunehmen , angewiesen war, um von jeder etwaigen Be wegung deS Gegners, welche von dieser Seite her die nachtheiligsten Folgen haben konnte, rechtzeitige Kennt ni\u00df ^u erlangen, sondern auch, in einem solchen Fall\u00ab, oder! bei einer \u00fcberlegenen Krafrentwicklung des Gegners\nnal Bianco als erste, \u00fcber den Adigerto als zweite, und endlich \u00fcber die Etsch als dritte Schutzstelluug bei einer retiograden Bewegung, zur\u00fcckziehen: die\u00df aber mit um so mehr Umsicht und Hartn\u00e4ckigkeit ausf\u00fchren, da diese Deiachirung von dem untern Po, r\u00fccksichr\u00fcch der dadur\u00abh erlangten Sicherung des Jnne- n der Venetianischen Pro vinzen , besondere Wichtigkeit darbiethet.!\u2014 ^J\u00e4hrend die ser\" Vorkehrungen zuy, Schutze der siiik-n Flanke deS 2. Reserve-CorpS harrx die Garnison von Malghera \u00abwen neuen Ausfall versucht, der aber eben so ung\u00fcnstig aus fiel, als alle fr\u00fcheren, und kr\u00e4ftig zur\u00fcckgewiesen wurde. \u2014 Auf dem linken Fl\u00fcgel in der Gegend von \u00c4ltine ver suchte der Feind den Posten aus dem Hause am Damme in der N\u00e4he der Batterie \u00ablel monte \u00e4'or\u00bb zu delogiren, indem sich die Angreifer in Barken zu n\u00e4hern suchten und ein heftiges Gewehr- und Gesch\u00fctzfeuer er\u00f6ffneten; die Mannschaft der PosteH des Wallachbanater - Regimentes wies jedoch standha t qlle Angriffe ab. Die Approvisionirung der Citadelle von Ferrara ging inde\u00df ziemlich rasch von Statten, und >s\u00bbar die Verbin dung zwischen Ferrara und Ponie lago scuro ganz frei; s\u00e4mmtliche Fahrzeugs auf der Strecke deS Po von Massa bis Polesella waren auf das linke Ufer geschafft, hier also dem Gegner dergestalt die Mittel zu einem schnelle\u00ab Uebergange mit gr\u00f6\u00dferer Truppenmacht benommen. I\u00bb Ponte di lago scuro und Stellata wurden die Befesti gungsarbeiten unter der Leitung des HaupcmanuS Ram-ming des Generalstabs th\u00e4tig betrieben, ohne da\u00df wei tere feindliche Bewegungen bemerkbar gewesen w\u00e4ren.\u2014 Wie mi\u00dff\u00e4llig alle di^se Anstalten dem Gegner waren, der durch den schnellen Angriff auf Fertara \u00fcberrascht, sich eiligst gegen Comacchio uud Bologna zur\u00fcckgezogen hatte, in welch letzterer Stadt die gr\u00f6\u00dfte Best\u00fcrzung eingetreten, die in f\u00f6rmliche Anarchie \u00fcberzugehen drohte, \u2014 bewiesen die unaufh\u00f6rlichen Recriminationen des p\u00e4pst lichen Prolegaten in Ferrara, \u00fcber angebliche GebiethS-verletzungen, Vertragsbruch uud Gewaltth\u00e4tigkeiten , di\u00ab sich jedoch alle auf jene Vorkehrungen beschr\u00e4nk\u00ab\u00bb, welche milit\u00e4rischeVorsicht gebothen. W\u00e4hrend jedochder Prolegat seine Prorestationenfortsetzte, hat sich der CardinalAmat nebst einem Piemontesischen StabSofficiere nicht entbl\u00f6det, die im p\u00e4pstlichen Solde stehenden, in die Capitulatioa von Vicenza eingeschlossenen Schweizertruppeo zum Bruche derselben und alsbaldig^r Ergreifung der Waffen gegen Oesterreich aufzufordern! > Die fr\u00fcher\u00ab auS 2VVV Mann Piemontesen, 2 Batail lons p\u00e4pstlicher Linientrvppen, 2 Escadrons CarabinierS und mehreren Abtheilungen Freischaaren bestehende Gar nison von Ferrara hatte sich g\u00e4nzlich zur\u00fcckgezogen und waren nur 450 p\u00e4pstliche J\u00e4ger und CarabinierS zur Aufrechthaltung der \u00f6ffentlichen Sicherheit zur\u00fcckgeblie ben , ZyV Mann der ersteren waren nach Venedig gesen det, der R\u00abst aber in Comaechi\u00bb verblieben. \u2014 W\u00e4hrend deS Vorr\u00fcckens der vom General-Major F\u00fcrst Liechten stein am linken Po-Ufer aufw\u00e4rts gesendeten Colonne hatte sich die Abtheilung unrer dem Herrn Oberstlieute nant Baron Sunstenau !auH 40 Compagnien deS Regie-menteS Prinz Emil bestehend, in Massa am 48. AbendS mit der auS 2^ Compagnien Graf Nugent Infanterie, 4 Gesch\u00fctzen und 6 Z\u00fcge\u00ab Carl Uhlane\u00fc zusammenge setzten Colonne des Herrn Oberstlieutenants Rosenbaum um 8UhrAbeuds vereinigt, und nahe am letzteren St\u00e4dt chen eiu Lager bezogen. Am 49ten Fr\u00fch waren die 4V Compagnien deS Regi mentes Emil sammt den 4 Gesch\u00fctzen und der Cavallerir nach Governolo unter F\u00fchrung deS Oberstlieutenants Sun stenau vorger\u00fcckt, stie\u00dfen jedoch bei diesem Orte auf\u00fcber-legene feindliche Kr\u00e4fte, wornach sie unter einem hartn\u00e4 ckigem Feuergefechte den R\u00fcckmarsch gegen Ostiglio an traten, das sie gegen Abend erreichten. In der Zwischen zeit war eine ansehnliche Abtheilung Piemontesen auS allen Waffengattungen zusammengesetzt, in Revere einge troffen , hatte ein heftiges Gesch\u00fctz- und Kle\u00fcigewehr-feuer gegen Ostiglia er\u00f6ffnet, daS \u2014 nachdem nun die beiden Abtheilungen von Nugent und Emil Infanterie wie- \""}