{"@context": "https://www.europeana.eu/schemas/context/edm.jsonld", "id": "https://www.europeana.eu/api/fulltext/9200300/BibliographicResource_3000051788869/da4ff9988ce1d6e82edf078f7ff793bb", "type": "FullTextResource", "edmRights": "http://creativecommons.org/publicdomain/mark/1.0/", "language": "de", "value": "TS\u00ab\n7Nckauons-Ku\u00abdmachjillg t ,'MG\u00ab\u00ab Lieferung . V^ FPapieMedsr^\u00bb \u00ab\u00bb d\u00bb\u00ab\nda\u00ab k. k. Galizi-Guhernium f\u00fcr die k. k. AatizischelEamerat - Gef\u00e4llen-Vevvaltung und f\u00fcridie \u00fcbrizen \u00abitWeneral - Pauschalien \u00abichtOMeilts-A k. k. Beh\u00f6vdes^j Anstalten im I Verwaltn nMatre t84S. Das k. k. Galizische \u00dfkiber\u00abium, die r. k. Galizische Ea-meral-Gef\u00e4llen-NerwaltunK und die \u00fcbrigen mit General-Dauschaiien \u00bbich\u00ab bethtilten k. k. Beh\u00f6iden, Aemter und An halten ben\u00f6thigen if\u00fcr da\u00ab Berwaltungsmhr 1849, da\u00ab ist f\u00fcr die Zeit vom t. Rov\u00abmber W48 bi\u00ab Enoe Oktober 184S fol gende Papier^ ltungem iabeyluufig n achst e hendenMengen!\nGr\u00f6\u00dfe\nBreite H\u00f6he\nZ-ll\nI. Das k. k. Galizische Subern.um ynp die \u00fcbrigen mit General-Pau'chalien nicht hetheil ten k k. Beh\u00f6rden, Aemter und Anstalten. tS Sag\u00ab f\u00fcnfzehn Rie\u00df Medi\u00e4n - Schreib papier . . . . > ... . . . Z2V0 Sage Eintausend zweyhundert Rie i Aanzley-Schreibpapier . . . zooo Sage zweyt\u00e4uftnd Rie\u00df Concept-Echreib parier . ^ ^ . . 500 Sage Einhundert Rie\u00df Gre\u00df-Packpapier 20 \u00bb zwanzig R e\u00df Kleitl-Packpapier II Die k k. Galizische vereint^ Cameral-Ge-f\u00e4llen Verwaltung, t) F\u00fcr da\u00ab k. Eackeral-Gef\u00e4llen-Berwal-tungis-O^konomat: LSV Satze achchundeit f\u00fcnfzig -Rie\u00df Klein-Eoncept-Schreibpapier. . . ... ISO Sage Einhundert f\u00fcnfzig Rie\u00df Gro\u00df-Concept-Schreihpapier . . ,, . 50Z0 Sage Eintausend drey\u00dfig Rie\u00df Alem-Aanzley-Schre>hpapier , . ... 4 Sage vier Rieb Kanzley-Gchreibpapier 4 \u00bb 1 Ms R>e\u00df Klein-FtsNpost'.Gchreib-\u00bbapifr ^ .. .\u00bb . . . . 2 Sage zw?y Rie\u00df Median-Fein - B?lin-Gchreibpapier > . . . . \u00bb . 8 Ga\u00e4e acht Rie\u00df Alein-Median-Schreib ^ ^ ^ \u00ab \u00bb \u00ab >\u00ab z) F\u00fcr die k. k. Aerarial Stein- und Buch druckerey: 10 Sage zehn Rie\u00df Super-R^gal-Kanzley-Schreibpapier. . . . . . . . 400 Sage vierhundert Rie\u00df Regal-Ka\u00fczley-Schreibp\u00e4pier . . ... . < i. 1750 Sage Eintausend' siebenhundert f\u00fcnfzig R e\u00df Ktein-Mehian-Schsieibpavisr > Z700 Sage Hintausei^d siebenhundert Rie\u00df MediatnPostdruckpapier . . . . S00 Sage neunhundert Rie\u00df Median-Post-druckpapipr/ . - . ... . 10 Sage z ehy R>e\u00df Post-Schreibpapier 52 Sage zw\u00f6lfZfie\u00dfFeinpost^Dchreibpapier gro\u00df FyrGat. ....... 12 Sage zw\u00f6lf Me\u00df Feinpost-Schreibpa-vier klein Formet . . . . . . zoso Gage Eintausend Rie\u00df Gro\u00df-Kanzley-Schreibpapier ....... zj00 Sage Ein tausend Einhundert Rie\u00df Klein-Aanzley-Schreibpapler. . . S40V Sage treytausepd vierhundert Rie\u00df Gro\u00df-Cqncspt Schreibpapier . . . 5200 Sage Eintausend zweihundert Rie\u00df Klein-C\u00f6ncept-Schreibpapier . . . Lt00 S\u00e4ge, zn^ey tauttnd Einhundert Rie\u00df ordin\u00e4res Druckpapier . . . Zur Sicherstellung diese\u00ab Bedarfe\u00ab wird eins Concilien; mittelst schriftlicher Kff\u00abrte bey der k. k. Cameral-Gef\u00e4llen-Verwaltung in LemHerg er\u00f6ffnet!. Die Offerte sind versiegelt, mit dem unten bestimmten Reugelde, oder mit dem legalen Beweise, da\u00df dasselbe bey einer Aerqxialcgssa zu Aieftm Zwecke erlebt worden sey, ver sehe\u00ab, \u00abW\u00ab-NMchtuAvvw.4Mu1erbKstn jeder zur Liefe rung angchplheneu Papiergatlung bi\u00ab einschlie\u00dfig Z0. August ^848 bey her k, k. Sameral-Ksf\u00e4llen-Perwaltung zu \u00fcber reichen, und mit der Ausschrift \u00bbAnboth zur Papierlieferung f\u00fcr da\u00ab VerwaltMlg\u00abjahr 1849\" zu bezeichnen. Nach Ablauf des, obige\u00bb Eoncurrenjlerckin\u00ab, d. i. nach dem 20. August 1848 werden keine Offerten mehr angenom men werden l Die Unterschriften der Offerenten sind mit dem Tauf- und Zunahmen, Charakter und AuftNthaltsoirt deutlich anzu setzen. , ! Die Offerten^ welche die ausdr\u00fcckliche Erkl\u00e4rung zu ent halten haben, da\u00df der Offerent sich de\u00fc Li!itation\u00abbedingnis-sen unbcd ngt unterziehen, werden in G\u00f6^enwart der hierzu testimwten Commission er\u00f6ffnet werden. Die L c tation\u00abbedingnisse sind folgende ! 1)' Ziir Lieferung kann sowohl B\u00fcttek- al\u00ab auch Maschi-\u00abenpaxier angebothen werten. Pon dezi,f\u00fcr die \u00abul, i an gef\u00fchrten k. ? Beh\u00f6rde\u00bb erforderlichen Pipieisoiten isi je-^rch der Uedarf an Mcdian-, dann an Gro\u00df- und Klein-P.ckpapicr g\u00e4nzlich, UN\u00bb jener an Eo.nceptSxapier zur Ha fte \u00bbN B\u00fcttenpapier zu lieftrn. > - .1 2) Die k- k- Ea^e^ral^Ges\u00e4llenxDerwaltung beh\u00e4lt sich die Wahl vor. entweder, dse gznze offe\u00abirte P. piermengs oder nur einen Theil hiervon, und zwar sowMbezstgl ch terver-\u00a7\u00bbietenen P\u00bbp ergatlungcn^l\u00ab auch in AbsiBt auf dir Meng\u00ab, \u00bbvn jede, Gattung anzunetn en, oder zur.ckzu\u00abeis<n.\n21^/,\n17\n1?V\u00bb\nIZV2\n17^'\u00bb 24-/\u00bb\n1Zt/z 21 IS\n17\nIZV2\n18 V\u00bb\nIS\n17 I8V2\nizVz IS\n17\n1^. z\n22t/z\n19\n22\n16V\u00bb\n26\n19\n24\nt8'/z\n22\nI6V2\n24\n18\n2Z 2Z\n18 18\n20\n1?\ntZVz\ntS\n17\n18^/z\nIS\n17\nizt/2\n17\ntZVs\nA) Nach Un st\u00e4nden werden auch LAttt^n auf einenT5eil i wat\u00ab - Oderbeawtsn, \u00abiper oder mehrerer P. pikrgaltungen beruck^chiigt werden. > Elein- und Buchdruckerey Statt findet, au\u00ab dem Drucken\u00bb\n4) Bon den nach der Wahl der k. k. TamtrOl -Gef\u00e4lleit-Berwaltung angenommenen Quantit\u00e4ten M ljer auf eik Bier^jahr entfallUtds^hsif vorhinein >im' \u00c4\u00bb\u00abf\u00ab tt\u00bb ersten Monathe\u00ab eine\u00ab jeden Quartal\u00ab an d\u00c4 V. Hameral-Ge-f\u00e4llsN-Ber\u00aba<tUng\u00ab-Se?vnvmat auf l\u00f6sten ie\u00ab Unternehmer\u00ab abzuliefern. Hinsichtlich der^ir die k. k. Aerapat Stein-und Buchdruckers in Lemberg bestimmten PapiS^gattungen hat diese Ablieferung an die letzlgenan- te Anst\u00e4w 5\u00bb geschehen. 5) Die offerirten Papiere sind sowohl der Quantit\u00e4t al\u00ab der Gattung nach genau u d die Preise in Eonvsntion\u00ab-M\u00fcnze nach dem Zwanzigguldenfu\u00dfe in Ziffern und Buch staben in dem Offerte au\u00abzudr\u00fccksn< k) Die Qualit\u00e4t det abzuliefernden Papiere\u00ab mu\u00df genau mit den vom Lieferanten vorgelegten, von der k. k. Same-ral-Gef\u00e4llen-V\u00abrwaltung gew\u00e4hlten, hiernach bezeichneten, und dem Lieferanten zukommenden Musterb\u00f6gen \u00fcberein stimmen. Auch k\u00f6nnen Musterb\u00f6gen von den bither verwendeten Pa piergattungen bey dem k. k. Cameral-Gef\u00e4llen-Verwaltun\u00e4\u00ab-Oekonomate, und bey derk k. Aerarial-DrHckerey-Direclion eingesehen werden S\u00e4mmtlichePapiergattunge^ mnssenau\u00ab keinhaternund ohne Beymischung von fremden Stoffen h\u00e4lt bar und dauerhaft verfertigt sevn, wie auch die angegebene H\u00f6he und Breite genau enthalten. 7) Wird ein Angeld (Vadium) von 5 pCt. des propomr-ten Preises der angebothenen Quantit\u00e4t gefordert, welche\u00ab entweder im Baren oder in \u00f6ffentlichen, nach dem letzbekann ten Wiener B\u00f6rservurse (bey Staatsschuldverschreibungen der beyden Votto-Anlehen von dem Zahre I8Z4 und 1833 nach dem Nennwerthe) z\u00ab berechnenden Oesterreichischen Staats-Obligationen zu leisten ist. Offerte ohne Angeld oder ohne die oben geforderte Er kl\u00e4rung werden nicht ber\u00fccksichtiget werden. 8) Eben sowenig wird auf Offerte R\u00fccksicht genommen werden, welche abweichende Nel'enbedingnisst enthalten, diese m\u00f6gen nun die Quantit\u00e4t des Papiere\u00ab oder die Art, oder die Zeit der Ablieferung betreffen. 9) Die Entschtidung wird \u00fcber eingeholte Genehmigung de\u00ab hohen k.k. Finanz-Ministerium\u00ab erfolgen, daherdieOffe renten bi\u00ab dahin Mit Verzichtleistung auf den im \u00a7. 862 des a. b. K. B. gesetzten Termin f\u00fcr ihre Anb\u00f6the verbindlich bleiben. 10) Diejenigen Prepvnenten, deren Anb\u00f6the von der Cameral-GeMen-Berw\u00c4Mnz mcht annchmbar befunden werden, erhalten da\u00ab Angeld sogleich zur\u00fcck. Da\u00ab Angeld derjenigen hingegen, de?e\u00bb AnboHe der h\u00f6 heren Best\u00e4tigung werden unterzogen werden, wird bis zur Best\u00e4tigung oder Zur\u00fcckweisung zur Sicherheit de\u00ab Aerar\u00ab zur\u00fcckbehalten melden, wo es sodann im ersten Fall\u00bb in die mit dem zehnten Theile de\u00ab ganzen Liefezungibelrage\u00ab zu leistende Caution eingerechnet oder im anderen Falle sogleich zur\u00fcckgestellt werden wird. it) Diese Caution, welche auf die in dem Abs\u00e4tze 7 der Licitativnibelingnisse angegebene Art geleistet werden Mu\u00df, und womit der Lieferant f\u00fcr alle aus d?m Vertrage ent springenden direkte\u00ab oder indirekten Ersatzleistungen zu b\u00e4 ten sich verpfliihtel, hat bi\u00ab zur g\u00e4nzlichen Erf\u00fcllung der un ternommenen Neferungsverbindlichkeiten erliegen zu bleiben, wo sie sodann gleich ausgefolgt werden chird. 12) Hach jeder geschehenen und annehmbar befundenen einzelnen Theill\u00fcferung wird her daf\u00fcr entfallende Verg\u00fc tung \u00abbetrag gegen classcnm\u00fc\u00dfig gest\u00e4mxelhe, von den z\u00fcr Uebernahme ds\u00ab Papieres berufenen Ob.rbeamtcn corami-sirte Q\u00fcit'ung sogleich ausgezahlt werden. 12) Die Zur\u00fcckstellung der Angeide zu den Offerten, wel che nicht ber\u00fccksichtigt oder nicht annehm-ar befunden werden, die Auszahlung der Verg\u00fctungtbetr\u00e4ge f\u00fcr geschehene und annehmbar befundene Lieferungen, dann die Zur\u00fcckstellung der Cautionen nach g\u00e4nzlicher E fullung der Vertragsver-bindlichselten geschieht an die Offerenten und Lieferanten se-bst oder an deren legal sich al\u00ab selche autweisenoen Be vollm\u00e4chtigte. Die die\u00dff\u00e4llige von den Machtgebern eigen h\u00e4ndig zu unterfertigenden und von der Personalgerichtt-baikeit derselben zu legalisirenden Vollmachten m\u00fcssen aber jede\u00ab einzelne dieier Gesch\u00e4fte besonder\u00ab bezeichnen. 14) Die Ablieferung de\u00ab Papier\u00ab hat vollz\u00e4hlig zu gesche hen, da\u00ab ist der Rie\u00df Papier mu\u00df 20 B\u00fccher, und ein Buch i beym Schreibpapiers B\u00f6gen, beym Druckpapier aber 25 B\u00f6-\" g n enthalten, und M- Gattungen muffen ohne Beif\u00fcgung irgend eine\u00ab Au\u00abschuffs\u00ab geliefert werden^ Die Schreibpapiere m\u00fcssen in einielnen Rie\u00dfen jeder Ries mit 2 Ejplagtb\u00f6gen vers\u00abh\u00abn (welche jedoch zu der Anzahl von 480 B\u00f6gen, au\u00ab tenen E>n Rie\u00df zu bestehen hat, nicht gerechnet werden d\u00fcrfen) und mit Bindfaden\u00ab gebunden, die Druckpapiere hingegen in ganzen B\u00f6gen breit gelegt, jeder Rie\u00df mit einem f\u00e4rbigewPapiere abgetheilt und zuioRie-\u00dfen gepackt seyn. 1\u00fc) Da e\u00ab nicht msglich ist jede einzelne Lieferung sogleich bey der Abstellung b\u00f6genweise durchz\u00bbsehen, und die allen-f\u00e4liige schlechte Qualit\u00e4t, oder den Abgang de\u00ab Papier\u00ab z , entdecke^, sy werden bey der U bernahme einer jeden Li-fe-rung vo? der Uebernahm\u00ab-Crmmiss.on sogleich einige einzelne Nie\u00dfe a^iKgeschieden, genau dm chgeseheN Md \u00fcberz\u00e4hlt wer ten, dersn Befund svdann f\u00fcr die ganze Lieferung in der Art zum Ma\u00dfstabe zu dienen hab.n wird, da\u00df. wenn z. B bey einer Ueberz\u00e4Klung von Z Rie\u00dfen ew Abgang von 2B\u00fc chern erhoben worden w\u00e4re, f\u00fcr eine Lieferung von KvRie-\u00dfen em Abgang von 40 B\u00fcchern angenommen werden w\u00fcrde. Zedoch bleibt e\u00ab d.m Ermessen der Uebernjahms-Commis-sion anheimg stellt, w'nn sie Grunde hierf\u00fcr zu haben glaubt, auch die ganze jedetmahlige Ablieferung gena^i durchzusehen und zu \u00fcberz -blen. 16) Alle Streitigkeiten, welche geeen da\u00ab Erkenntni\u00df der Uebcrnahm\u00ab -Commission, die sofern die Lieferung f\u00fcr da\u00ab k. k. GtM.n-OekonrWat gelchieht, au\u00ab den zwey Oekono-uttd sofern dieftlbe f\u00fcr die A-rarial-\nDii'ecter Md dem.Dn>ckereP-D'ch^ti\u00ab\u00bb\u00abMdjuncten, dann ei nem Oekonomats -\u00d6berb aP>t\u00abNg\u00bbu bestehen hat, \u00fcber' die Annehmbarkeit einer emzWe\u00ab ganze\u00ab, \u00bbder theitweise\u00bb Lieferung ^ntstLh\u00bb\u00ab's\u00bbkt\u00ab^^rd^ durch \u00abne \u00abvn der Ea-m-ral Gef\u00e4llen-Berchaltungi zu bestmnnende Commission nach erfolgter Einvernehmmsg von Sachverst\u00e4ndigen, und de\u00ab Liefe ranten, oder seines Bevollm\u00e4chtigten entschieden werde\u00bb, welcher Entscheidung ohn\u00ab weitere Berufung Folge geleistet w-rden mu\u00df. Gellte gegen den Lieferanten emschieden werden, so hat derselbe auch nebstbey die allenf\u00e4lligen Kesten dieser Commission zu bestreiten. 17) Der auf die oben bemerkte Art erhobene Abgang oder da\u00ab wegen schlechter Qualit\u00e4t oder sonstiger M\u00e4ngel zur\u00fcck gesto\u00dfene Papier mu\u00df durch vollkommen qualit\u00e4tm\u00e4\u00dfige\u00ab mit dem Musterbogen genau \u00fcbereinstimmende\u00ab Papier von derselben Gattung l\u00e4\u00fcgsten\u00ab innerhalb der Frist von 4 Wo chen ersetzt werden, \u00bbozu der Lieferant hiermit in\u00abbesondere verpflichtet wird. 18) Der Lieferant ist gehalten nach Bedarf auch mehr Pa pier al\u00ab er erstanden hat, um ten Erstehung\u00abprei\u00ab zu liefern, und zwar \u00fcber vorl\u00e4ufige yie w\u00f6chentliche Aufforderung, und bi\u00ab zu der Menge pe\u00ab vierten Theile\u00ab der ihm \u00fcberlassene\u00ab und von ihm \u00fcbernommenen Lieferung. Dagegen wir\u00bb dem Lieferanten zugesichert, da\u00df nicht weniger, al\u00ab die ihm \u00fcber lassenen Liefernng\u00dfquantit\u00e4t ovn der Zameral-G\u00abf\u00e4llen-Ber-waltung abgenommen werden wird. 19) Wird jede Bertragtverbindlichkeit al\u00ab eine Haupts\u00bb dingung de\u00ab Vertrage\u00ab e,kl\u00e4rt Wenn eine, \u00f6der die \u00e4ndM Bedingung nicht genau zugehalten, oder erf\u00fcllt werden sollte, so wir\u00bb die Eameral-Gef\u00e4llen-Verwallunz berechtiget seyn, den Vertrag entweder al\u00ab gebrochen anzusehen, und dieser? nere Lieferung auf Kosten und Gefahr de\u00ab contractSbr\u00fcchi-chen Lieferanten einer Relicitalion au\u00abzuseyen, oder den Lie feranten zur genauen ZuhaltUNg der eingegangenen Ber-tragsverpflichtungen zur verhalten, oder aber da\u00ab erforderli che Papier au\u00dfer dem Wege der Eoncurrenz durch freye\u00ab Handeinkauf ohne Cinvernchsnung de\u00ab Lieferanten, umw\u00ablch immer bestehende be iebige Preise beyschaffen zu lassen, ohne da\u00df der Zaternehmer gegen die g\u00abtr\u00bbMe Wahl de\u00ab au\u00ab-hiMwels\u00ab beyzuschaffen nothwendig gewordenen Papier\u00ab oder gegen die f\u00fcr da\u00absewe tugcstajldenxq Preise die geringst\u00bb Ein wendung zu macheii berech\u00f6g\u00f6t ist. Herner soll der Tameral-Gef\u00e4llen-Veriv\u00e4ltung da\u00ab Recht zustehen, den hieran\u00ab dem allerh\u00f6chsten Aerar allenfall\u00ab erwach eney Schaden au\u00ab der Caution und dem \u00fcbrigen wo immer vorfindigcn Verm\u00f6ge\u00bb de\u00ab contractbr\u00fcchigen Lieferanten einzubringen, dagegen soll der Contrahent auf den hiedurch etwa erzielten Vortheil kei nen Anspruch haben. 20) Werden d\u00abm best\u00e4tigten Lieferanten alle Rechtsmittel freygelassen, die er aii\u00ab dem Bertrage gegen da\u00ab allerh\u00f6chste Aerar in Anwendung bringet, zu k\u00f6nnen vermeint. 21) Ueber diese\u00ab Lieferungtgesch\u00e4ft wird ein Vertrag ap\u00ab-gefertigt werden,, dessen claffenma\u00dfige St\u00e4mplung der Liefe rant au\u00ab Eigenew zu bestreiten hat-Von der k. k. Galizischen Eameral-Gef\u00e4llen-Verwaltung. Lemberg den 23. Juliu\u00ab is48.\n^12Z07j\nHaus sammt Garten.\nVon der D. R. O. Landcommende Wien al\u00ab Herrschaft Hacking wird bekannt gemacht; E\u00ab sey wegen schuldiger 2800 fl. C. M. und 2ZS0 fl. C> M. c. \u00bb. e., die erecutive Feilbitthung deS auf80Z0st- C M. gesch\u00e4tzten Hause\u00ab Nr. Z4 sammt Garten in Hacking bewilllg 't, und zur,Vornabme der selben \u00fcber den fruchtlo\u00bb veistrichenen ersten Feilbiethung\u00ab-termin, der ZI. August d. Z. als zweyter uiO der 20. Sep tember d. I, als drister Termin mit dem Bsysatze bestimmt worden, da\u00df diese Realit\u00e4t, wenn st\u00ab bey dem zweyten Ter mine nicht wenigstens um den Sch\u00e4tzungswerth verkauft \u00aber kauft werden k\u00f6nnte, bey dem dritten Termine auch unter demselben h ndangegeben werden w\u00fcrde. \u2014 Die Licitativn wird an den obbezeichneten Tagen jedesmahl Vormittag\u00ab 10 Uhr bey dem Orttgerichte in Hacking abgehalten, und e\u00ab k\u00f6nnen die Feilbiethung\u00abbedingn sse t\u00e4glich Bormittag\u00ab vdn g \u201412 Ubr in der die\u00dfherrschaftlichen AmMaizsev im Deut schen Hause in der Stadt Nr. 879, VII. Stiege, III. Stock, einaesehen \u00aberden. . Wien am 1. August 1843.\n^i2vzs^ Licitation der Hauses Rr. zu Palt. Von der Stift\u00abherrschaft S\u00f6ttweig wird bekannt gemacht: E\u00ab sey in die neuerlich\u00ab \u00f6ffentliche Versteigerung, he\u00ab in die Verlasssnschafl\u00abmasse der zu Palt v rstvrbenen Anna Rausch, geh\u00f6rigen Hause\u00ab Nx. 12 zu Palt, mit dazu ges h\u00f6rigen G\u00e4rtchen, mit Bo,behalt der obercuratorischen Ra tifikation gewilliget, und zu, Vornahme der 24. August 184\u00ab Fr\u00fch S Uhr bestimmt werden > wozu Aaufiustige mit dem Beyf\u00fcgen eingeladen werden,! da\u00df die Licitation in de\u00ab z\u00ab ver\u00e4u\u00dfernden Hause vorgenommen werden wird. K\u00f6ttweig den 22. Zul u\u00ab 1848. ti.-i8o^ GassmHeleuchtungS-VerpKchtung. szI Vom gefertigten Grundgerichts wird, h\u00e4rmst bekannt ge geben, da\u00df die Gass.Meleuchtuyg M da\u00ab Berwaltung\u00abja\u00bbr 1849, n\u00e4hmlich f\u00fcr die Zeit vom 1. Noviember 1848 b>\u00ab EnKe Ocrober 1849, und zwar f\u00fcr alle Tage de\u00ab Z\u00e4hre\u00ab versteige rungsweise an den Mindestfvrdernden in Pacht \u00fcberlassen werden wird, zu welchem Ende eine L c tation auf d> n Ivten August d. Z., Fr\u00fch 10 Uhr, im Gemeindehause angeordnet wird. Die Pachtlust gen wollen sich demnach mit einer ivperc. Lauti,on de\u00ab E'stehung\u00abpre!fe\u00ab'Wfindcn. ! Die Bedingn sse k\u00f6nnen in der Grundgerichi\u00abkan zley ein-geschen werden. Grundgericht Mieden am 3. August 1848."}