{"@context": "https://www.europeana.eu/schemas/context/edm.jsonld", "id": "https://www.europeana.eu/api/fulltext/9200300/BibliographicResource_3000051824223/3ea8640a0eb5d9fa2f8c9c51ed8f1a7b", "type": "FullTextResource", "edmRights": "http://creativecommons.org/publicdomain/mark/1.0/", "language": "de", "value": "sZ! 5'<t. ZV!\njK, 'Ma\u00ab Ev.\nSonnen ^ Anf-sang.\nSv\u00abe't Unter,H.\nM. 24\nM s\nTagS\u00bb Las-ge.\nTi. \u00abU. 10 -'i!\nj15414 i\nHAR \">\u00bb>>>>\u00bb> s, >> > > Mete-^rckotzischr Beobachtungen an \u00bber Wiener Sternwarte am 16. October. ! ^\nZeit S\u00c4 B'-cdschr\nilhr M; M.r N. 1V tthr A.\nW\u00aboiWpk auf 0 Krad N^Stckt. red P-rikMa\u00dft \u00c4?sn. Ma\u00df 27^iS ZU 27.201 ZU 5\"\" 27,025 Z.! 27\" 9\"' 3\"\"\nThermo-meternach Rea\u00fcm\n-4- 7,8 -^-1?^7 -4- S V\nH\u00f6chste u. niSerste Temperatur bis \u00abU. M.-det.folgcn-den Tcges.\n-^-12 2\nlinde.\nSO stark. SO. stark. L. mitteim.\nltter\u00ab ng\nTritt\u00bb. Trl d. Mlk-n. -\u00bb\u00bb>\u00bb^\nDampfschiffahrt des\nOesterreich. Kloyd.\nWafferst^ad a\u00ab j?. October.\nAn der gro\u00dfen Vonaubr.\nZm Wiener Canale.\n-Sch. 2ZvS ober Null.\no. Wir.\nAbfahrt her Dampfboste von Trieft in den Monathen October, November und December 1848.\nMonathe\nN a -ch der Levante, j jeden zweiten Dinstag, \u00fcber Corfu und Syra nach Athen, Nauplia, Alexandrien, Scio-Cisme, Smyrna, (Mo dus, Cvrern, Bairut , Metelin, Uapjo-Baba, Tenedos, Dardanellen, Gallipoli, Salonich, CoUstantinopel, Zneboli, SZnore, Samsun, Tr\u00e4pezuntiVarna, T\u00fcltscha, Gamtz und Brail^\u00b0). In den Misen vom 24. October, 21. No\nvember u\n-October November December\n19. December. RK. T\u00bb. ?. S\u00bb. Z>. I\u00bb\nNach Griechenland, jeden zweiten Dinstag, \u00fcber Corfu, Pat^as, Vostizza nach Lu-traki, dann zu Lande \u00fcber den Isthmus von Korinth nach Calamaki, und von da nach Athen und Syra.\ns \u00bbe S8. \u00bb? SV\nMach Dalmatien,\n\u00fcber Liussinpiccolv, Zara, Spalato, Lestna, nach Sattaro.\nSebsmcv,\nDie directen Reisen nach Alexan-drien in Verbindung mit den Booten\nvon ^Bombay werden vomj. October l. Z. Curzola, Ragusajiskever beginnen, Md wiW die Abfahrt\nJeden Montag.\nz am 10. jeden Monaths von Trieft Statt ^ Anden. Dom Rovrtnber d. I. angeW-s gen, wird eine zweite direkte Reise in Z HqrbiWng mit Sen Bd\u00f6ken von Cal-j cutt\u00e4 beginnen, deren Avreise am ZK. z eine\u00df jeden Monaths von Trieft Statt ' finden wird.\n^ ... . i K ch 3 ft r t e n\u00bb Die Fahrten nach Venedig, Ancona und Brindtsi sind politiicher Verh\u00e4ltnisse Mittwoch und Samstag \u00fcber Pirano, Umago, Cittanuova, Parenzo, Rovig-vorl\u00e4ufig eingestellt. > Fasana nach Pola mit Ausdehnung der Samstag-Fahrt bis Fiume.\nDie Schiffe von Griechenland und den Zonischen Insel\u00bb sind in Trieft a u a r a nt\u00e4 nefr ei. Jene aus der Levante werden von Sanit\u00e4tsw\u00e4ch-Ueberfahrt gehalten, so da\u00df bei reinem Gestndheitspa\u00df die Passagiere sj>gseich bei Anku nft in Triest\nB e a cht e n s w^r th. tern begleitet', und deren Contumaz wird w\u00e4hrend der anden tonn ^ Reisen nach Vama, Tultscha, Gala^ und Braila werden bev Spsrrunz der Donau Mitte November eingestellt. Trieft, im October R848. Personen- und Frachten-Tarifes sind zu haben in der allgem. Privat-Gelch\u00e4ftskanzlei, Freiung Nr. 127\nMtteiMsis ia e. U.\n69 180\n17 October 1848. Lts\u00bbtZsvtiuIclve^?c'\"reit>ui>^eii ro \u00fc pLt !)\u00bbrlsdeo mit VerlosuuZ v. 1829 > k\u00f6r ZSg Z, ^r^rkarx\u00bb Kir tvv 2. Luri., FK\u00bb'A svrt\u00bb.Il. ZV.i\u00bb \u00bb\u00abt/,\u00bb.rv\u00bbFI NsMkarz, k\u00c4? ZLV L\u00bbu\u00abo, ktiiir, L.i\u00ab\u00bbr\u00abo, tn\u00bb Zvo l'o\u00bb\u00ab\u00bb\u00bb. I>ir\u00ab, Sr>t< , k\u00fcr z pkurxl LterlivZ, <-u!ck. ZSV O\u00bb\u00bb!\u00ab'\u00bb t,\u00bb\u00ab, N\u00bbrseiUe> kiir Z00 ?r,ulc\u00abn, ?\u00bbri\u00bb, f\u00fcr Z00 Die gro\u00dfe \u00f6ffentlich\u00ab Leihbibliothek von Armbrust\u00ab!\u00ab Witwe und Friedrich Gerold, in \u00bberGtadt, Singerstrase Nr. S?S, i\u00ab erste\u00abStock recht\u00ab, ist t\u00e4glich, \u00abit \u00bb\u00ab\u00ab\u00abahme der Go\u00bb\u00ab- \u00ab\u00ab\u00bb ?e\u00bber-tsze von \u00bb Uhr Fr\u00fch bi\u00ab \u00ab Uhr \u00abteads ge\u00f6ffn^\nft4ssi^ Die neue \u00f6ffentliche j^is^ S^vSSs-WKR\u00bbZS\u00abSS\u00bbek der Br\u00fcder I asper, am Kohlmarkt Nr. 114? und iiso (Hollauer'sches Haut) ist t\u00e4glich von. Fr\u00fch S bi\u00ab \u00bbbend\u00ab 7 Uhr ge\u00f6ffnet. PMiWM mqn\u00abhkich ist., j\u00e4hrlich to fi. C. M. Daselbst befindet sich auch ein Lager aller Gattungen linirter Handlungsb\u00fccher :c. von W.F. Zatper'\u00ab k. k. priv. Linir-Lnstalt, und werden Linir-Arbeiten jeder Srt dort \u00fcbernommen. Verstorbene zu Wien. Den 11. October. Dem Herrn Franz H\u00fctter, gewes. b\u00fcrgert. Strumpfwirker, seine Gattina Elisabeth, alt 7Z Z-, am Spitlberg Nr.lZZ, an Altersschw\u00e4che. Gregor Schlag. Knecht, glt so Z., von Sch\u00f6nfeld D. U M. B., an M fi\u00bb\u00bbg\u00abns\u00abtht^ te\u00bb d\u00ab, bafmhechisen Br\u00fcd\u00bbn. .. 1 Am, 12- OetOer. -Dem Hrn. Fohann Carl ^andrini, Schriftstell-r, seine Gat tinn Barbara, alt 27 Z., auf der Landstra\u00dfe Nr. LK8, an der Lungensucht. Dem Hrn Franz Zanitschek, Magistrat. Schlachtbr\u00fccken-Ober-auffther, sein Kind Franz, alt 6 I>, auf der Landst?as\u00b0 Nr.27S, an der Hirntuberkulose. DkM Joseph Weisort, Patental-Invaliden, seine Gattinn Anna, alt 48 Z,, auf der Landstra\u00dfe Nr. 167, am Zehr-fieb-r. Dem He nrich Schill, Zuckerb\u00e4cker, auf der M-d-n N r. 45^ wohnhast, sein Kind Hermine, all 4Z., am Waff r k\u00f6pfe, im Kinderspitals am Schaumburgergrun! Nr. 28.\nD^m Hrn. Zoseph Nikolay, b\u00fcrgl. Schuhmacher, sein Kind Maris, alt 2 Z., am Schottenseld Nr. 271, an der h\u00e4uti gen Br\u00e4une. Der Frau Theresia Huber, gepr\u00fcften Geburtshelferinn\u00bb ihr Kind Theresia, alt 2 Z., auf der Wiecen Nr. L<6,isn Fraisen. Maria Girss, Handarbeiierinn, alt 2\u00bbJ., an der Lungen tuberkulose, ira Bezirkskrankenhause auf der Meden. Zoseph Larosch, Kuxferdruck-r, alt S2Z>, ander Auszehrung, bey den barmherzigen Schwestern in Gumpendorf. Gkvrg Soratroi, Seieenf\u00e4rbergkselle, alt 42 2., an der Was sersucht, im k. k. allgemeinen Krankenhause. Den 12. October. Walburgi Greis, Waise, all 12 Z\u00bb, im Lichtenthal Nr. 64, an der Wassersucht. Der Frau Anna Marhart, Grei\u00dflers-Witwe, ihr Sohn Zo seph, alt 21 Z>, in der Levpoldstadt Nr. K64, an der Aus zehrung. Dem Johann Bischof, Tischlei gesellen,'sein Kind Rosa, alt 2Z., am Alsergrund Nr. 49, am Typhus. Herr Johann Kirchner, gew\u00abs. b\u00fcrgt. Shawlfabrika.it, alt 48 I., am Alsergrund ?kr. 40, an d\u00abr Lungenl\u00e4hmung. Dem Hrn. Zvst pH M\u00fcnster, b\u00fcrgl. Schneider, sein Kind Carl, alt 2 I., in Altlerchensel\u00f6 Nr. 24, an der Abzehrung. Herr Franz Kinzel, b-f. Mvrhg\u00e4rder, alt 61 I., auf der Windm\u00fchle Nr. 47, am Schlagflusse. > Frau Theresia Birner, b\u00fcrgl. Webers-Witwe, alt 70 I., in ^ Gumpendorf Nr. S25, an Altersschw\u00e4che. ^ Dem Hrn. Anton Franchi, k. k. Beamien, seine Gattinn Rosa,! !alt 65Z., am Spitlberg Nr. 124, an der Lmigsnl\u00e4hmung., Herr Johann Fiftl, Doctor d.-r Medicin, Mitglied der me- ! dirinischen Facult\u00e4t und HauSinhaber, all 72 Z., zu St, -Ulrich Nr. 100, an Entkr\u00e4ftung. Dem Leopold Allmann, Tischle, gesellen, sein Kind Amalia, alt 2J , auf der Wieien Nr. 2iv, an der Lungenent z\u00fcndung. tisssz^ Anzeig e. !.-Da\u00bb mit der Wohnung ies G feitigten in Verbindung\nstehende, mit einer Nachtglvcke versehene chirurgische Ordi-nalion\u00ab Locale in der Levpoldstadt, neue Gaffe Nr. 122, ersten Stock, mit allen chirurgischen Instrumenten, Banda gen und einer NsthapotHeke zugleich zum Slettungs-Locale eingerichtet, wird bey ejtws vorkommenden Verw\u00fcndunjjen oder sonstigen Ungl\u00fccksk\u00e4llen zu jeder Stunde des Tages und der Nacht hiermit Zedermann freundlichst angebothen. Unter Einem zeig! der Gefertigte die Stunden von 7 tiS 8 Uhr Morgens und von 2 tiS 4 Uhr Abend\u00ab als die t\u00e4g lichen Ordinationsstunde\u00bb in allen chirurgischen F\u00e4lle\u00bb f\u00fcr die Bezikks-Armen an. Wien am 15. October 1848. Eduard Russer, Dr. der Medicin und Chirurgie, Magister der Gebmtth\u00fclfe, im Wiener k. k. chirurgischen Operation\u00ab - Institute gebildeter Operateur, Stadtkavptmannschaftlicher Bezirkt-Wundarzt der Levpoldstadt und Z\u00e4gerzeile. l>54\u00bbi Wrlornes Kind. N Samstag am ZV. September d. I., Vormittags nach 8 Uhr, kam das 7 Zshre alte M\u00e4dchen Theresia Kronber-ger beym Ausgange au\u00ab der Kirche zu St. Ulrich in Wien, am Platz!, von ihrer Begleitung abhanden, ohne bisher a\u00ab\u00ab-gemittelt zu werden. Dieses Kind ist von Ober-\u00c4ohrbach Nr. 67 bev Korneubkrg, hat blaue Augen, blond Haare, ist nach Ait der Landkinder gekleidet, und wei\u00df sich gut a\u00abK-zudrucken. Wer n\u00e4here Auskunft \u00fcber den Aufenthalt diese\u00ab Kindes zu geben verckag, erh\u00e4lt 5 ff. CM- Belohnung. Herrschaft Jedlersdorf den 14. Octobsr 184S. ^5551! ^ Der p\u00e4dagogische Berein , in Wien bat wegen der traurigen Ereignisse seine S tzungen f\u00fcr den Mcnalh October aufgehoben. V a u l B s r n h a r d, Stellvertreter de\u00ab V. Pr\u00e4se\u00ab.\n^S1V8Z\nK. K pr. Wbe Dampf-Schiffahrt\nzwischen rag und Dresden und retoiir den 19. 21. 22. 2S. 27. 29. 21. October. Abfahrt von Prag um 5 Uhr Fr\u00fch. Zur Bequemlichkeit des Publicums ist ein Theil des Schlosses Obrigw\u00bb (Landungsplatz) altH\u00fcteleingerichtet nebst bester Bedienung, wodurch das zu fr\u00fche Aufstehen g\u00e4nzlich beseitigt werden k\u00f6nne. Bureau: Drey Karpfen Kolowrststra\u00dfe Nr. 8S2.\n^>54SZ^\nAn die W\u00e4hler des Bezirkes Neunkirchen.\nMeine Herren! Ein langwieriges Uebel sowohl alt ein Werk, welches ich zu unternehmen gedenke, erlauben mir nickt l\u00e4nger, ununterbrochen den Kammer verhandlungen beyzuwohnen, ich habe au\u00ab diesem Grunde meinen Austritt be reits anqezeigt. Indem es Ihnen nun \u00fcberlaffen ist, einen W\u00fcrdigeren zu w\u00e4hlen, danke ick Zhnen \u00abiederhohlt f\u00fcr diese ehrenvolle Auszeichnung, und w\u00fcnsche meinem Nachfolger Gl\u00fcck eine so ausgezeichnete W\u00e4hlerschaft vertreten zu k\u00f6nne\u00bb\u00ab Wien am II. Octob-r iS48. F. Staudenheim."}