{"@context": "https://www.europeana.eu/schemas/context/edm.jsonld", "id": "https://www.europeana.eu/api/fulltext/9200300/BibliographicResource_3000051818057/fd7bb686d6aa0732f1f2ce377361fa7a", "type": "FullTextResource", "edmRights": "http://creativecommons.org/publicdomain/mark/1.0/", "language": "de", "value": "Prinumeratiovi - Preis f\u00fcr Wie\u00ab: auf Druckpapier ganzj\u00e4hrig 20 fl., halbj\u00e4hrig 10 fl., viertelj\u00e4hrig b fl. C. M.; a\u00bbf \u00c4clinpapier ganzj\u00e4hrig 32 fi., halbj\u00e4hrig 16 st., viertelj\u00e4hrig 8 fl. C. M. Einzelne Bl\u00e4tter koste\u00bb 30 kr. C. M.\nesterreichisch-\nKaiserlich\nJnsertivns-Geb\u00fchr f\u00fcr die einspaltige Petitzeile bei einmahliger Eiubruckunz \u00e4 kr. E. M., f\u00fcr die zweite u\u00bbd dritte Wiederhohlung jedesmahl 2 kr. <5. M., folglich f\u00fcr dreymahlige Eiudruckung S kr. C. M.\n^ sz\nDonnerstag ten SS. M\u00e4rz\nInhalt.\nAmtlicher Theil. Nicht-amtlicher Theil. Inland. Wie\u00bb. M\u00e4hren und Schlesien. KSrnthen. Lo\u00ab\u00bb. Benet. K\u00f6nigreich. Ungarn. Dentfchland. Preu\u00dfen. Patent wegen beschleunigter Einberufung des vereinigten Landtages. \u2014 Gesetz Aber die Presse. Baiern. Die Zust\u00e4nde in M\u00fcnchen. Hannover. Proclamation des K\u00f6nigs. W\u00fcrtem-berg. Stuttgart. Ludw.Uhland.K urHessen. Sitzung des Landtags. Braunschweig. Einberufung der St\u00e4nde. Sardinien. Nachrichten auS Genua. Kirchenstaat. Aufruf Sr. Heiligkeit. K\u00f6nigreich beider Gictlien. Entbindung der K\u00f6 nigin.\nInland.\nAmtlicher Theil.\nWien. 3\u00c4ir Ferdinand der Erste, von Gotte\u00bb Gna den Kaiser von Oesterreich; K\u00f6nig von Huugarn und B\u00f6hmen, dieses Nahmens der F\u00fcnfte, K\u00f6nig der Lombardei und Venedigs, von Dalmatien, Croatien, Slavonien, Galizien, Lodomerien und Jllirien; Erzherzog von Oesterreich; Herzog von Lothringen, Salzburg, Steiermark, K\u00e4rnthe\u00ab, Krain, Ober- und Nieder - Schlesien; Gro\u00dff\u00fcrst von Siebenb\u00fcrgen; Markgraf von M\u00e4hren; ge-f\u00fcrsteter Graf von Habsburg und Tirol ?c. :c. Um Unseren getreuen Unterthanen einen \u00abeitere\u00bb Be weis Unseres Vertrauens zu geben , und ihnen zu zeigen, wie sehr Wir geneigt sind, selbst gegen Verirrte Gnade tu \u00fcben, sohin von dem UnS die\u00dffalls zustehenden Rechte Gebrauch zu mache\u00ab , haben Wir Uns bewogen gefunden, insbesondere r\u00fccksichtlich Unserer K\u00f6nigreiche Galizien und Lodomerien, dann deS Lombardisch-Venetianischen K\u00f6nig reiches folgende Bestimmungen zu treffe\u00bb: Erstens: S\u00e4mmtlichen in den K\u00f6nigreiche\u00ab Galizien und Lodomerien, mit Einschlu\u00df deS Krakauer Bezirkes, dann im Lombardisch-Venetianischen K\u00f6nigreiche wegen HochverrathS oder St\u00f6rung der inneren Ruhe des Staa tes in Untersuchung gezogenen, und gegenw\u00e4rtig in der Strafe befindlichen Individuen vom Civilstande ist die noch \u00fcbrige Strafzeit nachgesehen, sofern sie nicht auch anderer Verbrechen schuldig erkannt worden sind. Zweitens: Bez\u00fcglich der bei den Gerichten der gedach ten K\u00f6nigreiche wegen solcher Verbrechen verhaftete\u00ab/ aber noch nicht definitiv abgeurtheilten Individuen soll , jedes weitere Verfahren niedergeschlagen, und eine neue Unter suchung wegen \u00e4hnlicher Thatsachen, welche dieser Unserer Entschlie\u00dfung vorausgegangen sind, nicht mehr eingeleitet werden; jedoch sollen die im ersten und in dem gegen w\u00e4rtigen Abs\u00e4tze erw\u00e4hnten Individuen\u00bb wenn sie Aus-linder sind, sogleich auS Unseren Staaten abgeschafft werden, und dieselben nur mit Unserer ausdr\u00fccklichen Erlaubni\u00df wieder betreten d\u00fcrfen. Drittens: Jene Leute aus den gedachten K\u00f6nigreichen, welche, weil sie in politische Umtriebe verflochten, oder dabei compromittirt waren, an einen andere\u00bb Ort confi-r-irr wurden, sind in den Genu\u00df ihrer Freiheit zu setzen\u00ab Viertens: Diejenigen, welche auS gleichen Gr\u00fcnden einem speciellen Verbothe unterzogen wurden, sind von diesem loszuz\u00e4hleu. Sonach erwarten Wir mit Zuversicht, da\u00df durch diese Unsere Bestimmungen die Gem\u00fcther sich beruhigen, Ruhe und Ordnung \u00fcberall zur\u00fcckkehren, und Unsere getreuen Unterthanen UnS die Liebe und Anh\u00e4nglichkeit beweisen werden, die sie bei so vielen Gelegenheiten r\u00fchmlichst be w\u00e4hrt haben. Gegeben in Unserer kaiserlichen Haupt- und Residenz stadt Wien, den zwanzigsten M\u00e4rz, im Eintausend acht hundert acht und vierzigsten, Unserer Reiche im vier zehnten Jahre. Ferdinand. (1^. 8.) Franz Graf von Kolowrat, prov. Minister-Pr\u00e4sident. Ludwig Graf von Taaffe, Minister der Justiz. Franz Freiherr von Pillers dorff, Minister des Inneren-Nach Sr. k. k. apostol. Majest\u00e4t H\u00f6chst eigenem Befehle : Wenze\u00f6law Ritter von ZaleSki, k. k. Hofrath.\ngenden Geiste wird auch fernerhin die kr\u00e4ftige Leitung dei vaterl\u00e4ndischen Angelegenheit\u00ab, auf der Bahn des Fort schrittes Statt finden. Wien am 22. M\u00e4rz 4848. Alfred F\u00fcrst zu Windischgr\u00e4tz, ^ k. k. Feldmarschall-Lieutenant. Zur Erg\u00e4nzung und Verst\u00e4rkung des prov. B\u00fcrger-Aus-schuffeS, aW\u00df dessen Mitte laut hierortiger Kundmachung vom 47. d. M. mehrere Mitglieder den Verhandlungen bei den Ni. HA. Herren St\u00e4nden beigezogen werden, und zum Ersatze d\u00dfG freiwillig ausgetretenen pr. Ausschusses Herrn I. B. Venvenuti, wurden durch die Herren \u00e4u\u00dferen Stadtr\u00e4the und Gemeinde - Repr\u00e4sentanten nach benannte Herren zu Mitgliedern deS prov. B\u00fcrger-Aus schusses ernannt, als: Franz AloiS Bernard, Mitglied deS \u00e4u\u00dferen Stadt-ratheS. Joseph Buchwein, Grundgerichtsbeisitzer der Ge meinde Mieden. Georg Hartl, b\u00fcrgl. Seifensieder. Paul Herther, Mitglied deS \u00e4u\u00dferen StadtratheS und Richter der Gemeinde Hundsthurm. Franz Jacks, b\u00fcrgl. Zimmermeister und Richter d<r Gemeinde Ro\u00dfau. Anton Kilian, Mitglied deS \u00e4u\u00dferen Stadtrathis und b\u00fcrgl. Handelsmann. Franz K\u00fchn, Vorstand des b\u00fcrgl. B\u00e4ckermittels. Johann Langer, Mitglied deS \u00e4u\u00dferen Stadtrath\u00abS und Grundgerichtsbeisitzer der Gemeinde Leopoldstadt. Peter Poafickl, Mitglied deS \u00e4u\u00dferen Stadtra thes und Richter der Gemeinde Alservorstadt. Jos. Schmiedt, Richter der Gemeinde Josephstadt. Leopold v. Wertheimstein, Prokuraf\u00fchrer des Hau ses Rothschild. Carl Winkler v. Forazest, Mitglied des \u00e4u\u00dfe ren Stadtrathes uad.b\u00fcrgl. Einhandlet. AloisWuest v. Wellberg, Vorstand der b\u00fcrgl. Tuchscherer. Vom Magistrate und prov. B\u00fcrger-Aussch\u00fcsse der Stadt Wien am 20. M\u00e4rz 4848.\nSe. k. k. Majest\u00e4t haben mit Allerh\u00f6chster Entschlie\u00dfung vom 49ren l. M., die bei der Jnternuntiatur in Con-stantiuopel erledigte dritte Dolmetschstelle dem dortigen Secret\u00e4r - Dolmetsch, Theodor Ritter v. Schwarz-Hub er, unter Belassung seines dermahligen Titels zu verleihen geruhet. Se. k.k. Majest\u00e4t haben mit Allerh\u00f6chster Entschlie\u00dfung vom 3. M\u00e4rz l. I., dem Hofrathe und Obersthofpost-Verwylter, Ritter von Ottenfeld, die Annahme und das Tragen deS ihm von Sr. k\u00f6nigl. Hoheit dem Her zoge von Parma verliehenen Ritterkreuzes 4ster Classe deS Constantinischen St. Georg-OrdenS von Parma aller-gn\u00e4digst zu gestatten geruhet. Die Aufgeregtheit im \u00f6ffentlichen Leben und Treiben hat sich bei uu\u00bb gelegt; und somit haben auch die au\u00dfer ordentlichen milit\u00e4rischen Ma\u00dfregeln ihr Ende gefunden, zu deren Ergreifung mich unser angebetheter Kaiser in Mitte ersch\u00fctternder Ereignisse bevollm\u00e4chtigte. Bei der so schweren Stellung, welche mir daS Ver trauen deS Monarchen in diesem weltgeschichtlichen Mo mente an den Stufen des Thrones anzuweisen geruhte, f\u00fchle ich mich dankbar gedrungen, der achtbaren B\u00fcrger wehr aller Classen der Residenz aufrichtige Anerkenu\u00abvg daf\u00fcr auszusprechen, da\u00df deren Besonnenheit mir meine schwere Pflichterf\u00fcllung erleichterte. AbermahlS mu\u00df Europa anerkennen, da\u00df Festigkeit gepaart mit vaterlicher Milde die Grundmaxime Oester reichischer Regierungsweise ist, und in diesem heilbrin\nNicht\u00bbamtlicher Theil. Oesterreichs Weltstellung. \u00bbKeine Zeit und keine Macht zerst\u00fcckelt \u00abGepr\u00e4gte Form, die lebend sich entwickelt.\u00ab Mit diesen Worten unseres gro\u00dfen DichrerS schlo\u00df ich meine zweite Ansprache an die \u00f6ffentliche Meinung, worin ich auf die Nothwendigkeit einer gemeinsamen, alle Na tionen des Reiches umfassenden und mit starker Nieder-k\u00e4mpfung kleiner nationaler Empfindlichkeit ins Leben tre tenden Staats-Idee die Aufmerksamkett zu lenken mir er laubte. In ruhiger Weiterspinnuug des Gedankenfadens begann ich daS dritte Wort an mem Volk zu schreiben: \u201eEwe Idee bedarf, wenn sie nicht verk\u00fcmmern soll ihreS Tr\u00e4gers. Die Trager der Ideen sind Einrichtungen, in denen sie bewahrt, gepflegt, der Erinnerung der Menschen vor Augen gehalten und mit den Organen ihrer Wirksam-kelt ausgestattet werden. Und eine Idee, welche daS ganze Kaiserreich mit Le-bevsf\u00fclle durchdriugen soll, bedarf einer eben auch das ganze Kaiserreich umfassenden Institution u. s. w.- Und m einem andern Blatte: \u00bbder rothe Faden in der Welt geschichte- versuchte ich das fortschreitende System deS po litischen Bed\u00fcrfnisses, das die h\u00f6here Menschenvatur cha-rakterisirt, hervorzuheben, seufzend unter dem, den Flug des Gedankens l\u00e4hmenden, in schmerzlichen Wehen vor-empfuadeue\u00bb Drucke der Censur. \u2014 Da kam es, mir dem raschen G\u00f6tterschritte, daS herr liche Geschenk unseres gro\u00dfen, jetzt durch die Liebe seiner ihm zujubelnden Millionen un\u00fcberwindlich-m\u00e4chtigen Kai sers, daS herrliche dreifache Geschenk, das am 45. M\u00e4rz Thr\u00e4nen der undegr\u00e4nzten Freude, Thr\u00e4nen deS tiefge f\u00fchltesten NarerlandSstolzes entlockte jedem, sogar dem trockensten ManneS-Auge, daS seit Jahren diesen s\u00fc\u00dfen Thau des Gef\u00fchls nicht gekostet. Wir hielten es zitternd in unseren H\u00e4nden und riefen jubelnd: nun stehen wir wieder an der Spitze Deutschlands uad treten mit ihm aa die Spitze der Weltgeschichte! \u201eund keine Zeit und keine Macht zerst\u00fcckelt gepr\u00e4gte Form, die lebend sich ent wickelt.\" So haben die Ereignisse den schwachen Bestrebungen auf eine alle Berechnung \u00fcberfl\u00fcgelnde Weise gl\u00fccklich und ruhmw\u00fcrdig vorgegriffen; und ganz wie der Dichter sagt, so wird es nun in alle Zukunft sein mit unserem gro\u00dfen v\u00f6lkerverbindenden Oesterreich, nachdem eS in den drei entscheidendste\u00ab Tagen seiner Geschichte jene Einrichtungen erhalten hat, welche als die Tr\u00e4ger der Idee und als die VermittlungSorgane f\u00fcr die wettere Entwicklung seines reichen Inhaltes unerl\u00e4\u00dflich waren. Jetzt kann es nicht mehr innerlich klein bleiben, eS kann nicht mehr unter halben Ma\u00dfregeln verk\u00fcmmern, eS mu\u00df mit gewaltigem Fl\u00fcgelschtage sich emporschwingen zu jener H\u00f6he, zu der eS bestimmt ist in der Weltgeschichte. Da\u00df wir uns dieser Bestimmung und Aufgabe vollkom men klar bewu\u00dft werden, ist nun unsere Sache. Die Stel-lung, welche Oesterreich in der Europ\u00e4ischen Staaten-Fa milie nach seinem historisch gegebenen Berufe einnimmt, ist viel zu bedeutungsvoll, als da\u00df wir sie nicht einer reif lichen Erw\u00e4gung unterziehen sollte\u00ab, jetzt, nachdem die Mittel der Vollstreckung dieser Aufgabe gegeben sind, nach dem man unS nicht mehr, wie eS ehemahls geschah, sagen kann: Tr\u00e4umer was willst du mit deinen weitansreichen-den Ideen in dieser dem allmahligen Zerbr\u00f6ckeln geweihten morschen engherzigen Welt? Mit Zagen war man bisher gew\u00f6hnt auf die Verschie denartigkeit der Oesterreich bewohnenden V\u00f6lker zu blicken. Weil man die Verschiedenheit in diesem Ma\u00dfe ander w\u00e4rts nicht sah, glaubte mau hierin den schwachen Punct zu finden. Die\u00df ist ein unerme\u00dflicher Irrthum. Gerade in dieser Eigenth\u00fcmlichkeit Oesterreichs liegt seine welt geschichtliche Bedeutung; in ihr liegt der Keim einer gro\u00df artigen Zukunft; durch sie steht eS einzig da und ist ein nothwendige\u00ab Glied in der Kette der Europ\u00e4ischen Gesell schaft dergestalt, da\u00df es geschaffen werden sollte, wenn es nicht da w\u00e4re. Es ist von unendlicher Wichtigkeit, da\u00df die Wahrheit\ndieses SatzeS in vns festen Boden fasse, weil er die be-gl\u00c4keude\u00ab Bande, mit welchen die Constitution des ge meinsamen Vaterlandes unS umschlingen wird, noch fester uich \u00abnaufl\u00f6Slicher kn\u00fcpft. Ich werde versuchen, mich n\u00e4her zu erkl\u00e4ren. Wo immer verschiedene Nationen ohne scharfe nat\u00fcr liche Gr\u00e4nzen in abgesonderten Staatsorganismen Uneben einander wohnen, sind von Zeit z\u00ab Zeit Reibungen >nd Zusammenst\u00f6\u00dfe unvermeidlich. Der National-Hoch-\u00abath, bekanntlich ein scharfer Sophist und Dialectiker, fi\u00bbdet leicht einen Anla\u00df, welcher ihn bestimmt, dem EroberuugSgel\u00fcste Raum zu geben; in der Eroberung, in Sieg \u00fcber ein anderes spiegelt stch die Herrlichkeit und \u00dcberlegenheit der geistigen und physischen Kraft eineS Volkes. In dem Momente hingegen, in welchem die verschie de\u00ab\u00ab Nationen zu Einem Staatsleben zusammen gefa\u00dft \u00aberden, h\u00f6rt der Kampf unter ihnen auf, denn sie m\u00fc\u00df-t\u00ab B\u00fcrgerblut vergie\u00dfen, l\u00e4hmen die eigene Kraft und drr Welt anstatt des Schauspiels der Herrlichkeit und Gr\u00f6\u00dfe ein Schauspiel des JammerS und der Erb\u00e4rmlich kit geben. In Europa sind drei gro\u00dfe V\u00f6lkerfamilien, welche das Scepter der Weltgeschichte in der Hand tragen: Die Germaoen, Romanen und Slave\u00ab. Ferner gibt eS ein Gebieth i\u00ab Europa, wo diese drei V\u00f6lkerfamilien zusam mensto\u00dfen, dergestalt, da\u00df in demselben auch das verein zelt stehende, keiner der drei Familien angeh\u00f6rende Volk wohnt. Dieses Gebieth ist daS Oesterreichische StaatSge-bieth, mit seinen Deutschen, Italienischen uud Slavischen St\u00e4mmen und mit seinem Ungarischen ganzen Volke. Es war ein er der genialsten Gedanken der Weltgeschichte\u2014 auf diesem Gebiethe ein m\u00e4chtiges Kaiserreich entstehen zulassen. Es hat in sich die drei V\u00f6lkerfamilien aufgenommen, und eben dadurch de\u00ab gegenseitigen physische\u00ab Kampf aufgeho ben, um qn seine Stelle den geistigen Wettkampf treten zu lassen. Aus dieser Betrachtung wird Oesterreichs Bestimmung klar, als Europ\u00e4ischer Friedenshort Kampf zn verh\u00fcthen, und friedliche Entwicklung zu pflegen unter den Europ\u00e4i schen V\u00f6lkerfamilien. Hegel sagt in seiner Philosophie der Geschichte ungef\u00e4hr: Oesterreich sei darum ein wahres Kaiserreich, weil eS aus der Zusammensetzung, der von verschiedenartige\u00ab V\u00f6lkern bewohnten Lande und K\u00f6nig reiche erwachsen ist, durch welchen wesentlichen kaiser-th\u00fcmlichen Charakter eS sich von allen anderen Staaten uud Gro\u00dfm\u00e4chten unterscheidet und gewisserma\u00dfen einen welthistorisch h\u00f6heren Standpunct einnimmt. Nach dieser Auffassung unseres gro\u00dfen Philosophen gibt es nur Ein Kaiserreich in der Welt, obgleich skh dieses Titels meh rere anma\u00dfen, die\u00df Eine ist Oesterreich, denn kein ande res fa\u00dft in sich die weltbeherrschenden V\u00f6lkerfamilien, die nationalen Geister der Germaoen, Romanen uud Slaven zu einer gro\u00dfen Ehrfurcht gebiethenden Macht, zu ge meinsamer h\u00f6chster Herrlichkeit zusammen. Aus diesem Grunde wage ich eS die Bestimmung Oesterreichs als m\u00e4chtigen Friedens Hortes unter den drei V\u00f6lker familien und durch sie selbst, seine kaiserliche Be stimmung zu nennsn. Oesterreichs Bestimmung hat aber noch eine andere Seite mehr innerlicher Natur. Wenn der Europ\u00e4ische Frieden, in sofern er durch den Gegensatz der Nationen hervorgerufen werden k\u00f6nnte, seine \u00e4u\u00dfere Bestimmung ist, so hat es auch durch die eigenth\u00fcmlich verbundenen Kr\u00e4fte eine tiefere humanit\u00e4re Bedeutung. Die verschiede ne\u00ab nationellen Genien gravitiren um ihren eigenen beson deren Mittelpunct; so kommt es, da\u00df die Germanen eine Sympathie durchzieht, welchem der Regel da hervortritt, wo daS Germanische Element mit dem Romanischen oder Slavischen in Conflict kommt; eben so bei den Romanen uud Slaven. In allen aber lebt zugleich eine mehr allgemeine Sym pathie, getragen und gef\u00f6rdert von der allgemeinen Mensch-Heits-Jdee. Vereinzelte Erscheinungen dieses rei\u00ab mensch lichen Dranges zeigen sich in den logenannten Cosmopoli-ten, in dem \u201eseid umschlungen Millionen,- in religt\u00f6sen Secten. Dieses menschliche Bed\u00fcrfni\u00df m\u00f6chte ich dahin ausdr\u00fccken, da\u00df die verschiedenen nationellen Geister nm die Menschheits-Idee gravitiren. Eine bessere Verk\u00f6r perung dieses h\u00f6heren nationellen Gravi-t atiooS-Draoges, als Oesterreich, gibt eS nicht und zwar aus demselben Grunde den man zum Beweise seiner Schw\u00e4che anf\u00fchren zu d\u00fcrfen glaubte, n\u00e4hmlich aus dem Grnude, weil es der Mittelpunkt der drei weltgeschicht lichen V\u00f6lker - Familien ist , und zugleich eine Gro\u00dfmacht \u201eumwallt von un\u00fcberwindlichen Marken- dem Auge dar stellt. Wenn daher irgend ein Staat, so ist Oesterreich f\u00e4hig, auf dem gro\u00dfartigen Fu\u00dfe seiner materiellen Mit tel und auf dem hoheu Staudvuucte seiner bewegenden Ideen die humanit\u00e4re Entwickelung im Gegensatze zu einer blo\u00df beschr\u00e4nkt - nationellen auf seine Fahne zu schreiben, und dieselbe unter der F\u00fchrung seines glorreichen und gelieb ten Kaisers dem gesammteu Europa vorau zu tragen. Alle seine V\u00f6lker werden ihm mit Freuden auf dieserBahn folgen, sie werden ihren Standpunct h\u00f6her fa\u00dfen, als die V\u00f6lker anderer Staaten, weil ihre Bestimmung eine h\u00f6here ist; eS werden \u201ein dem gemeinsamen Streben, in dem gemein samen Ziel, in der Erinnerung des gemeinsamen Gef\u00f6r derten, die Traditionen ehemahliger Stammverwandtschaft erbleichen \u2014 im Hochgef\u00fchle einer neuen h\u00f6 her stehenden Nationalit\u00e4t.\" (s. A.A.Z. vom 46. M\u00e4rz.) So gestaltete sich vor unseren Augen von je die Be stimmung Oesterreichs, seine nothwendige Entwicklung, seine Weltstellung: \u2014 EineS fehlte: jene Einrichtung, welche zum Tr\u00e4ger dieser Idee geeignet war und zugleich den Stolz deS Oesterreichisch-kaiserlichen Bewu\u00dftseins zu begr\u00fcnden verm\u00f6gend sein sollte. Die\u00df Eine, was uns fehlte, ist da \u2014 und nun ist rS unsere Pflicht, dem gro\u00dfen, weltgeschichtlichen Gedanken, dem mir ange h\u00f6ren, unsere ganze Kraft zu weihen zur Verherrli chung unseres Kaisers, zu unserer eigenen Verherrlichung, zur Erf\u00fcllung unserer historischen Pflicht. Alle kleinli chen , separatistischen, engherzigen, provinzth\u00fcmelnden, empfindelnden Gedanken, welche verzeihlich waren, so lange der Gedanke eines gro\u00dfen Oesterreichs uoch verh\u00fcllt war, sie alle m\u00f6gen auf deu Altar deS gemeinsamen Va terlandes niedergelegt werden. Eine Sonne ist in Oester reich aufgegangen und in der Sonne m\u00f6gen sterben die kleinen Flammen. Dr. Johann Perthaler.\nRede am Grabe der am 43. und^.M\u00e4rzGe-fallenen, gesprochen von Professor Anton R\u00fcster. --\u2014\u2014-\u201eES gibt gro\u00dfe Stunden im menschlichen Leben, Stun den , in welchen die Kraft deS Geistes sich in all' ihrer Herrlichkeit offenbart, Stunden, in welchen die Sieges-krafr des Geistes alle Schrecken der Erde, selbst die Schre cken des Todes \u00fcberwindet. Diese Stunden verk\u00fcnden, beweisen, \u201eda\u00df wir g\u00f6ttlichen Geschlechtes sind.\" Solche Stunden schlugen unS dieser Tage, solche Stunden durch lebten die k\u00e4mpfenden Oesterreichischen Vaterlandsfreunde, die Helden der ewig unverge\u00dflichen M\u00e4rztage, der Tage, an welchen die harte, tiefe Eisdecke eineS langen Winters brach, gel\u00f6st durch den Flammenhauch der Begeisterung f\u00fcr Wahrheit, Recht und Freiheit. Wer kann solche er habene Momente schildern, wer kann die innigsten mensch-heitbewegenden Gef\u00fchle beschreiben, wer kann die Helden w\u00fcrdig loben, welche freudig ihr Leben in die Schanze schlagen, welche ihr Leben freudig opfern f\u00fcr die Br\u00fcder!\" \u201eUnd die gegenw\u00e4rtige Stunde ist sie nicht auch eine gro\u00dfe Stunde! Erfassen unS nicht in diesen Momenten ernste, erhebende Gedanken, heilige, tiefe Gef\u00fchle, ent z\u00fcndet sich an diesem gro\u00dfen Grabe nicht eine unausl\u00f6sch liche Begeisterung f\u00fcr Wahrheit, Recht und Freiheit! best\u00e4tigen nicht selbst diese Leichen die Worte deS Philoso phen: \u201eDer Duft der Geisterwelt dringt \u00fcberallhin.\" \u201eIdeen bewegen die Menschheit, eine einzige Idee bewegt ganze V\u00f6lker.\u00ab Gro\u00dfe Stunde, in welcher wir die Lei-name der f\u00fcr daS Vaterland Gefallenen in das Grab versenken, in welcher wir Samenk\u00f6rner der reinsten, durch den Heldentod geweihten Vaterlandsliebe in die Erde streuen! Aus diesen Samenk\u00f6rnern erw\u00e4chst eine ewige Saat der Ermunterung zur Vaterlandsliebe, verk\u00fcndend die Kraft deS menschlichen Geistes, der Ideen, die Kraft deS menschlichen Herzens, der Bruderliebe!\" \u201eIm Nahmen meiner hochverehrten Herren College\u00bb, der Mitglieder der philosophischen Facult\u00e4t, spreche ich an diesem gro\u00dfen Grabe (wohl nur schwach) aus die Gef\u00fchle, welche uns bewegen, unsere innigste Verehrung, die wir den Gefallenen weihen, unsere innigste Dankbarkeit f\u00fcr die Vaterlandsliebe, die sie mit ihrem Blute besiegelt! Hei! Ihnen, sie starben den sch\u00f6nsten Tod , den Tod f\u00fcr daS Vaterland; Heil Ihnen! sie opferten sich f\u00fcr eine gro\u00dfe Idee! Sie verk\u00fcnden die Herrlichkeit, die Siegeskraft der Ideen!j Sieget ihr heil. Ideen! Es siege die Wahr heit, die HimmelStochter, bei deren Nahmen die Herzen im Hochgef\u00fchle schlagen ! ES siege daS Recht, daS unver \u00e4u\u00dferliche , dem Menschen angeborne, von Gott gehei ligte , daS Recht, das feste Band der Gesellschaft! ES siege die Freiheit, die Schwester des Rechtes, die Schwe ster des Friedens und der Liebe! Wahrheit, Recht, Frei heit, Liebe, sollen siegen \u00fcber unsere Feinde! Die Liebe soll unS Alle vereinigen als Kinder eineS Vaters im Him mel, alS Kinder eineS VaterS auf Erden, in Oesterreich, unsers g\u00fctigsten Kaisers Ferdinand! AlS Br\u00fcder, die f\u00fcr einander Gut und Blut opfern!\" \u201eDu Mutter-Erde! bewahre die gro\u00dfeu Samenk\u00f6rner, welche wir dir anvertrauten, trage die himmlische Sa\u00fct, welche auS ihnen erw\u00e4chst! Du heil. St\u00e4tte, worauf wir weilen, verk\u00fcnde auch du allen Zeiten die Worte deS ewi gen Meisters: \u201eEine gr\u00f6\u00dfere Liebe hat Niemand als wer daS Leben gibt f\u00fcr die Br\u00fcder.\" Ihr Verherrlichten, wir danken Euch auS der Tiefe deS HerzenS, denn ihr fielet f\u00fcr unS! Freuet euch deS SiegeS, ihr habet ausgek\u00e4mpft; euch bl\u00fcheu hiernieden Ehrenkr\u00e4nze, welche nie welken, euch bl\u00fcht ewiger Ruhm! Ruhet im Frieden! Und du, hochherziges Oesterreich, Gott segne dich mit seinem Frie den! Amen!\" Rede, gesprochen vo\u00ab Professor Anton F\u00fc-ster^ am Grabe der in de\u00bb M\u00e4rz fUlilienen bei der Bestattung des Humani-t\u00e4ts-Sch\u00fclers Carl Konitscheck, am 49ten M\u00e4rz 4848. \u201eHeldenj\u00fcnglinge Oesterreichs, studierende J\u00fcnglinge, Vork\u00e4mpfer f\u00fcr Wahrheit, Recht und Freiheit, Sie haben ohngeachtet der rauhen Witterung einen Mitsch\u00fcler zur letzten Ruhest\u00e4tte geleitet. Das siebzehnte Opfer das zur Rettung deS Vaterlandes gefallen, versenkten \u00abir in daS gro\u00dfe Grab. Der J\u00fcngling ist zu seinen Mitbr\u00fc dern gesellt worden in dem gro\u00dfen Grabe, daS den sp\u00e4 testen Zeiten verk\u00fcnden wird die glorreichen M\u00e4rztage, an welchen Oesterreich in Freiheit erstand, sich anreihete den freien Staaten der Erde; an welche\u00ab Oesterreich, Oesterreich, daS erste freie Reich deS Ostens ward; an welchen der neubelebende Sch\u00f6pfuugShauch durch ein gro\u00dfes Reich wehete, damit eS seine zahllosen Keime der physi schen und moralischen Kr\u00e4fte zur herrlichen Gottessaat entwickle!\" \u201eAuch du edler J\u00fcngling hast am glorreichen 43ten M\u00e4rz geblutet und starbst nach gro\u00dfen Schmerzen f\u00fcr daS Vaterland. Heil dir, du hast unverg\u00e4nglichen Ruhm errungen!\" \u201eMutter, dir ward der einzige Sohn, deine Freude, dein h\u00f6chstes Gl\u00fcck entrissen; deinen guten Sohn, der die St\u00fctze deines AlterS sein sollte, hat dir der Wahn ge-t\u00f6dtet. Arme Mutter, wer kaun deine Schmerzen schil dern ! Deinen im Studium und in Tugend ausgezeichne ten Sohn hat man dir gemordet! Und doch rufe ich dir zu: Weine nicht! Mutter, weine nicht, dein Sohn starb den sch\u00f6nsten Tod, den Tod f\u00fcr daS Vaterland! Dein Sohn ist ein Vorbild der Jugend geworden, ein Vorbild der Vaterlandsliebe! Dein Sohn ruhet in dem Grabe, daS eine Ehreust\u00e4tte Oesterreichs bleibt zu jeder Zeit. Dein Sohn starb jung, aber er hat mehr erworben alS Tausende in dem l\u00e4ngsten Leben erwerben, den unverg\u00e4ng lichen Ruhm!\" \u201eStudierende J\u00fcnglinge! unsere Freude, unser Stolz! Sendbothen der Wahrheit, des Rechtes und der Freiheit, erhalten Sie sich die edle Begeisterung f\u00fcr Ihren hohen Beruf, deu Muth f\u00fcr alle Gefahren, die Th\u00e4tigkeit f\u00fcr das Wohl deS Vaterlandes! Blicken Sie auf Ihren ge fallenen Mitk\u00e4mpfer uud geloben Sie sich, keine Gefahr, selbst den Tod nicht zu scheuen, wenn Wahrheit, Recht und Freiheit dieses Opfer fordern! Studierend\u00ab Jugend, du bist der lebeuSfrische Ausdruck deS Zeitgeistes i Dr\u00fccke auS deu Zeitgeist durch unausl\u00f6schliche Begeisterung f\u00fcr Wahrheit, Recht uuh Freiheit!\" \u201eHeldenm\u00e4nner Wiens! Edle B\u00fcrger WienS! Wie gl\u00fccklich sch\u00e4tze ich mich Ihr Mitb\u00fcrger zu sein, in Ihrer Mitte zu wohnen, dazu leben wo so biedere Herzen schla gen, wo so gro\u00dfer Edelmuth waltet, wo so klare Ansich-"}